tb/PE_sva.sv
// reset properties
property rst_n_property;
    @(posedge clk)
    !rst_n |=> (
        dut.A_forw_reg       == 8'b0  &&
        dut.B_forw_reg       == 8'b0  &&
        dut.mult_reg         == 16'b0 &&
        dut.mult_valid_reg   == 1'b0  &&
        dut.accum_reg        == 32'b0
    );
endproperty

assert property (rst_n_property)
    else $error("Reset operation failed");


// forwarding properties
property forwarding_property;
    @(posedge clk)
    disable iff (!rst_n)
    (pe_valid && !accum_clr) |=>
    (
        dut.A_forw_reg == $past(A) &&
        dut.B_forw_reg == $past(B)
    );
endproperty

a_forwarding: assert property (forwarding_property)
    else $error("Operand forwarding property failed");


// Product properties
// Product clear
property product_clear_property;
    @(posedge clk)
    disable iff (!rst_n)
    accum_clr
    |=> (
        dut.mult_reg         == 16'b0 &&
        dut.mult_valid_reg   == 1'b0
    );
endproperty

a_product_clear: assert property (product_clear_property)
    else $error("Product pipeline was not cleared");


// Product Capture
property product_capture_property;
    @(posedge clk)
    disable iff (!rst_n)
    (pe_valid && !accum_clr) |=>
    (
        dut.mult_reg ==
            ($signed($past(A)) * $signed($past(B))) &&
        dut.mult_valid_reg == 1'b1
    );
endproperty

a_product_capture: assert property (product_capture_property)
    else $error("Product capture failed");


// Product dealing with Bubble (pe_valid = 0)
property product_bubble_property;
    @(posedge clk)
    disable iff (!rst_n)
    (!pe_valid && !accum_clr)
    |=> (
        dut.mult_valid_reg == 1'b0
    );
endproperty

a_product_bubble: assert property (product_bubble_property)
    else $error("Product-valid was not cleared after a bubble");


// Accumulation Stage

// Product Valid high
property p_valid_product_accumulates;
    @(posedge clk)
    disable iff (!rst_n)
    (!accum_clr && dut.mult_valid_reg)
    |=> dut.accum_reg ==
        ($past(dut.accum_reg) + $past(dut.mult_reg));
endproperty

assert property (p_valid_product_accumulates)
    else $error("Accumulator did not add the previous valid product");


// Product reg when accum_clr is high
property p_clear_accumulator;
    @(posedge clk)
    disable iff (!rst_n)
    accum_clr |=> (dut.accum_reg == '0);
endproperty

assert property (p_clear_accumulator)
    else $error("Accumulator was not cleared");

src/PE.v
/* 

Processing Element ( Qty = 4) 
- 1 Product reg and 1 Accum reg 
- Forwarding reg x 2 for both A and B (forwards to the next PE horizontally/vertically)
- Priority of flags : rst_n > accum_clr > PE_valid > valid_A/B or mult_reg_valid

*/
module PE (
    input clk, 
    input rst_n,
    input pe_valid, 
    

    input signed [7:0] A , 
    input signed [7:0] B ,  
    output signed [31:0] C ,

    

    input accum_clr,                         // begin a new matrix multiplication / clear the previous C result 

    output signed [7:0] A_forw_op,           // corresponding 8 bit forwarding output for A/B_forw_reg (F1) 
    output signed [7:0] B_forw_op

);
 reg signed [15:0] mult_reg ; 
 reg mult_valid_reg;                         // whether the product stored in mult_reg is valid and should be accumulated (F3)
 
 reg signed [31:0] accum_reg ; 
 
 // Fowards operands to the neighboring PE 
 reg signed [7:0] A_forw_reg ;
 reg signed[7:0] B_forw_reg ;

     // Operands Forwarding               
always @(posedge clk) begin
    if (!rst_n) begin 
        A_forw_reg  <= 8'b0;
        B_forw_reg  <= 8'b0;
    end 

    else if (pe_valid && !accum_clr) begin 
        A_forw_reg <= A; 
        B_forw_reg <= B; 
    end 
    // inffered latch since accum_clr condition not included ? 
    // Need to firgure out what would happen to the forw_registers if Accum_clr is hi and PE_valid = 0/1 
end 

// Operands forwarding 
assign A_forw_op = A_forw_reg ;
assign B_forw_op = B_forw_reg ;

// Product Pipeline Stage
always @(posedge clk) begin
    if (!rst_n) begin
        mult_reg       <= 16'b0;
        mult_valid_reg <= 1'b0;
    end
    else if (accum_clr) begin
        mult_reg       <= 16'b0;
        mult_valid_reg <= 1'b0;
    end
    else if (pe_valid) begin
        mult_reg       <= A * B;
        mult_valid_reg <= 1'b1;
    end
    else begin
        mult_valid_reg <= 1'b0;  // Bubble; previous product can still be accumulated on this edge
    end
end 

// Accumulation Stage 
always @(posedge clk) begin 
    if (!rst_n) begin 
        accum_reg   <= 32'b0; 
    end 
    else if (accum_clr) begin 
        accum_reg   <= 32'b0; 
    end 
    
    else if (mult_valid_reg) begin 
        accum_reg   <= accum_reg + mult_reg  ;  
    end 

end 
// connecting the accum reg to the final C 
assign C = accum_reg ; 



endmodule

tb/PE_tb.sv
`timescale 1ns/1ps

module PE_tb;

    // DUT inputs driven by the testbench
    logic clk;
    logic rst_n;
    logic pe_valid;
    logic accum_clr;

    logic signed [7:0] A;
    logic signed [7:0] B;

    // DUT outputs observed by the testbench
    wire signed [31:0] C;
    wire signed [7:0]  A_forw_op;
    wire signed [7:0]  B_forw_op;

    // Device Under Test
    PE dut (
        .clk        (clk),
        .rst_n      (rst_n),
        .pe_valid   (pe_valid),
        .A          (A),
        .B          (B),
        .C          (C),
        .accum_clr  (accum_clr),
        .A_forw_op  (A_forw_op),
        .B_forw_op  (B_forw_op)
    );

    // 10 ns clock period
    initial begin
        clk = 1'b0;
    end

    always #5 clk = ~clk;

    // Basic directed stimulus
    initial begin
        // Safe initial values
        rst_n     = 1'b0;
        pe_valid  = 1'b0;
        accum_clr = 1'b0;
        A         = 8'sd0;
        B         = 8'sd0;

        // Synchronous reset across two rising clock edges
        repeat (2) @(posedge clk);

        // Deassert reset away from the active sampling edge
        @(negedge clk);
        rst_n = 1'b1;

        // Idle cycle
        @(negedge clk);
        pe_valid = 1'b0;

        // Clear before starting a new operation
        @(negedge clk);
        accum_clr = 1'b1;

        @(negedge clk);
        accum_clr = 1'b0;

        // First valid operand pair
        pe_valid = 1'b1;
        A        = 8'sd3;
        B        = -8'sd2;

        // Second valid operand pair
        @(negedge clk);
        pe_valid = 1'b1;
        A        = -8'sd4;
        B        = 8'sd5;

        // Bubble containing intentionally dangerous data
        @(negedge clk);
        pe_valid = 1'b0;
        A        = 8'sd99;
        B        = 8'sd99;

        // Additional drain cycle
        @(negedge clk);
        pe_valid = 1'b0;

        // Clear the completed result
        @(negedge clk);
        accum_clr = 1'b1;

        @(negedge clk);
        accum_clr = 1'b0;

        // Allow the simulation to continue briefly
        repeat (2) @(posedge clk);

        $finish;
    end

    // Optional waveform generation
    initial begin
        $dumpfile("PE_tb.vcd");
        $dumpvars(0, PE_tb);
    end

    /*
     * Add your SVA properties here.
     *
     * Public DUT signals:
     *   rst_n, pe_valid, accum_clr
     *   A, B, C, A_forw_op, B_forw_op
     *
     * Internal DUT state can currently be observed using:
     *   dut.mult_reg
     *   dut.mult_valid_reg
     *   dut.accum_reg
     *   dut.A_forw_reg
     *   dut.B_forw_reg
     */
     
`include "PE_sva.sv"



endmodule

PE_tb.vcd
$version Generated by VerilatedVcd $end
$timescale 1ps $end
 $scope module $rootio $end
 $upscope $end
 $scope module PE_tb $end
  $var wire 1 - clk $end
  $var wire 1 # rst_n $end
  $var wire 1 $ pe_valid $end
  $var wire 1 % accum_clr $end
  $var wire 8 & A [7:0] $end
  $var wire 8 ' B [7:0] $end
  $var wire 32 ( C [31:0] $end
  $var wire 8 ) A_forw_op [7:0] $end
  $var wire 8 * B_forw_op [7:0] $end
  $scope module dut $end
   $var wire 1 - clk $end
   $var wire 1 # rst_n $end
   $var wire 1 $ pe_valid $end
   $var wire 8 & A [7:0] $end
   $var wire 8 ' B [7:0] $end
   $var wire 32 ( C [31:0] $end
   $var wire 1 % accum_clr $end
   $var wire 8 ) A_forw_op [7:0] $end
   $var wire 8 * B_forw_op [7:0] $end
   $var wire 16 + mult_reg [15:0] $end
   $var wire 1 , mult_valid_reg $end
   $var wire 32 ( accum_reg [31:0] $end
   $var wire 8 ) A_forw_reg [7:0] $end
   $var wire 8 * B_forw_reg [7:0] $end
  $upscope $end
 $upscope $end
$enddefinitions $end


#0
0#
0$
0%
b00000000 &
b00000000 '
b00000000000000000000000000000000 (
b00000000 )
b00000000 *
b0000000000000000 +
0,
0-
#5000
1-
#10000
0-
#15000
1-
#20000
1#
0-
#25000
1-
#30000
0-
#35000
1-
#40000
1%
0-
#45000
1-
#50000
1$
0%
b00000011 &
b11111110 '
0-
#55000
b00000011 )
b11111110 *
b1111111111111010 +
1,
1-
#60000
b11111100 &
b00000101 '
0-
#65000
b11111111111111111111111111111010 (
b11111100 )
b00000101 *
b1111111111101100 +
1-
#70000
0$
b01100011 &
b01100011 '
0-
#75000
b11111111111111111111111111100110 (
0,
1-
#80000
0-
#85000
1-
#90000
1%
0-
#95000
b00000000000000000000000000000000 (
b0000000000000000 +
1-
#100000
0%
0-
